{
  "name": "dashboard",
  "version": 32,
  "source-key": {
    "type": "figma",
    "file": "5CLGcKnas0I545VDpxUew6",
    "node": "467:346",
    "version": "4665963787",
    "component-id": "437bd2a358cc083b83ee61bbea7ceaf93bbc7b8a"
  },
  "default": "Dashboard",
  "design": {
    "atoms": [
      {
        "type": "group",
        "id": "top_level",
        "root": "true"
      },
      {
        "type": "group",
        "id": "Ready"
      },
      {
        "type": "text",
        "id": "Welcome Back, John"
      },
      {
        "type": "group",
        "id": "Menu Banner"
      },
      {
        "type": "vector",
        "id": "Rectangle 53"
      },
      {
        "type": "group",
        "id": "Next"
      },
      {
        "type": "vector",
        "id": "Vector"
      },
      {
        "type": "text",
        "id": "Ready to schedule your pickup?"
      },
      {
        "type": "vector",
        "id": "Rectangle 80"
      },
      {
        "type": "text",
        "id": "Next1"
      },
      {
        "type": "vector",
        "id": "Rectangle 33"
      },
      {
        "type": "group",
        "id": "Navy logo"
      },
      {
        "type": "group",
        "id": "Menu"
      },
      {
        "type": "group",
        "id": "Clip path group"
      },
      {
        "type": "group",
        "id": "Clip path group1"
      },
      {
        "type": "group",
        "id": "Logo"
      },
      {
        "type": "group",
        "id": "573b9caeaf"
      },
      {
        "type": "group",
        "id": "Group"
      },
      {
        "type": "vector",
        "id": "Vector1"
      },
      {
        "type": "group",
        "id": "Mask group"
      },
      {
        "type": "group",
        "id": "Group1"
      },
      {
        "type": "group",
        "id": "Group2"
      },
      {
        "type": "group",
        "id": "Group3"
      },
      {
        "type": "group",
        "id": "Group4"
      },
      {
        "type": "image",
        "id": "Rectangle"
      },
      {
        "type": "group",
        "id": "Group5"
      },
      {
        "type": "image",
        "id": "Rectangle1"
      },
      {
        "type": "group",
        "id": "b4bab9ea00"
      },
      {
        "type": "group",
        "id": "Group6"
      },
      {
        "type": "vector",
        "id": "Vector2"
      },
      {
        "type": "group",
        "id": "Group7"
      },
      {
        "type": "image",
        "id": "Rectangle2"
      },
      {
        "type": "group",
        "id": "Clip path group2"
      },
      {
        "type": "group",
        "id": "695a20c734"
      },
      {
        "type": "group",
        "id": "Group8"
      },
      {
        "type": "vector",
        "id": "Vector3"
      },
      {
        "type": "group",
        "id": "Group9"
      },
      {
        "type": "image",
        "id": "Rectangle3"
      },
      {
        "type": "image",
        "id": "Menu1"
      }
    ],
    "modes": {
      "Dashboard": {
        "rules": [
          {
            "id": "top_level",
            "is-structured": "false",
            "children": [
              "Ready",
              "Welcome Back, John",
              "Menu Banner"
            ],
            "background-color": {
              "alpha": "1.0",
              "hue": "198.0",
              "saturation": "0.11764705882352944",
              "value": "1.0"
            }
          },
          {
            "id": "Ready",
            "alignment": {
              "horizontal": {
                "attachment": "start",
                "offset": "34.0"
              },
              "vertical": {
                "attachment": "start",
                "offset": "142.0"
              }
            },
            "size-constraints": {
              "width-constraints": {
                "sizing-mode": "fixed",
                "value": "291.0"
              },
              "height-constraints": {
                "sizing-mode": "fixed",
                "value": "305.0"
              }
            },
            "is-structured": "false",
            "children": [
              "Rectangle 53",
              "Next",
              "Vector",
              "Ready to schedule your pickup?"
            ],
            "clip-content": "false"
          },
          {
            "id": "Welcome Back, John",
            "alignment": {
              "horizontal": {
                "attachment": "start",
                "offset": "45.0"
              },
              "vertical": {
                "attachment": "start",
                "offset": "70.0"
              }
            },
            "size-constraints": {
              "width-constraints": {
                "sizing-mode": "fixed",
                "value": "260.0"
              },
              "height-constraints": {
                "sizing-mode": "fixed",
                "value": "60.0"
              }
            },
            "color": {
              "alpha": "1.0",
              "hue": "0.0",
              "saturation": "0.0",
              "value": "0.0"
            },
            "text-content": "Welcome Back, John",
            "overflow": "visible",
            "max-lines": "-1",
            "text-align-vertical": "center",
            "text-size": "25.0",
            "line-height": "1.210227279663086",
            "typeface": "Inter"
          },
          {
            "id": "Menu Banner",
            "size-constraints": {
              "width-constraints": {
                "sizing-mode": "fixed",
                "value": "360.0"
              },
              "height-constraints": {
                "sizing-mode": "fixed",
                "value": "38.0"
              }
            },
            "is-structured": "false",
            "children": [
              "Rectangle 33",
              "Navy logo",
              "Menu"
            ],
            "clip-content": "false"
          },
          {
            "id": "Rectangle 53",
            "border-radius": "30.0",
            "size-constraints": {
              "width-constraints": {
                "sizing-mode": "fixed",
                "value": "291.0"
              },
              "height-constraints": {
                "sizing-mode": "fixed",
                "value": "305.0"
              }
            },
            "vector-content": "rectangle_53.svg"
          },
          {
            "id": "Next",
            "border-radius": "30.0",
            "alignment": {
              "horizontal": {
                "attachment": "start",
                "offset": "71.0"
              },
              "vertical": {
                "attachment": "start",
                "offset": "233.0"
              }
            },
            "tap-handler": "$Next",
            "size-constraints": {
              "width-constraints": {
                "sizing-mode": "fixed",
                "value": "150.0"
              },
              "height-constraints": {
                "sizing-mode": "fixed",
                "value": "50.0"
              }
            },
            "is-structured": "false",
            "children": [
              "Rectangle 80",
              "Next1"
            ],
            "clip-content": "false"
          },
          {
            "id": "Vector",
            "margin": {
              "left": "86.070068359375",
              "top": "123.28277587890625",
              "right": "106.0599365234375",
              "bottom": "92.28173828125"
            },
            "size-constraints": {
              "width-constraints": {
                "sizing-mode": "proportional",
                "value": "1.0"
              },
              "height-constraints": {
                "sizing-mode": "proportional",
                "value": "1.0"
              }
            },
            "vector-content": "vector.svg"
          },
          {
            "id": "Ready to schedule your pickup?",
            "alignment": {
              "horizontal": {
                "attachment": "start",
                "offset": "9.0"
              },
              "vertical": {
                "attachment": "start",
                "offset": "35.0"
              }
            },
            "color": {
              "alpha": "1.0",
              "hue": "0.0",
              "saturation": "0.0",
              "value": "1.0"
            },
            "annotated-text-content": {
              "text": "Ready to schedule\n your pickup? ",
              "annotated-text-span-list": [
                {
                  "span-start": "0",
                  "span-length": "31",
                  "annotated-text-style": {
                    "text-size": "30.0"
                  }
                },
                {
                  "span-start": "31",
                  "span-length": "1"
                }
              ]
            },
            "overflow": "visible",
            "text-size": "12.0",
            "line-height": "1.2102272510528564",
            "typeface": "Inter"
          },
          {
            "id": "Rectangle 80",
            "border-radius": "30.0",
            "size-constraints": {
              "width-constraints": {
                "sizing-mode": "fixed",
                "value": "150.0"
              },
              "height-constraints": {
                "sizing-mode": "fixed",
                "value": "50.0"
              }
            },
            "vector-content": "rectangle_80.svg"
          },
          {
            "id": "Next1",
            "alignment": {
              "horizontal": {
                "attachment": "start",
                "offset": "41.0"
              },
              "vertical": {
                "attachment": "start",
                "offset": "5.0"
              }
            },
            "size-constraints": {
              "width-constraints": {
                "sizing-mode": "fixed",
                "value": "97.0"
              },
              "height-constraints": {
                "sizing-mode": "fixed",
                "value": "40.0"
              }
            },
            "color": {
              "alpha": "1.0",
              "hue": "0.0",
              "saturation": "0.0",
              "value": "1.0"
            },
            "text-content": "Next",
            "overflow": "visible",
            "max-lines": "-1",
            "text-align": "left",
            "text-size": "30.0",
            "line-height": "1.2102272033691406",
            "typeface": "Inter"
          },
          {
            "id": "Rectangle 33",
            "size-constraints": {
              "width-constraints": {
                "sizing-mode": "fixed",
                "value": "360.0"
              },
              "height-constraints": {
                "sizing-mode": "fixed",
                "value": "38.0"
              }
            },
            "vector-content": "rectangle_33.svg"
          },
          {
            "id": "Navy logo",
            "alignment": {
              "horizontal": {
                "attachment": "start",
                "offset": "13.0"
              },
              "vertical": {
                "attachment": "start",
                "offset": "0.0"
              }
            },
            "size-constraints": {
              "width-constraints": {
                "sizing-mode": "fixed",
                "value": "149.942138671875"
              },
              "height-constraints": {
                "sizing-mode": "fixed",
                "value": "37.66668701171875"
              }
            },
            "is-structured": "false",
            "children": [
              "Clip path group",
              "Clip path group1",
              "Logo"
            ],
            "clip-content": "false"
          },
          {
            "id": "Menu",
            "alignment": {
              "horizontal": {
                "attachment": "start",
                "offset": "318.0"
              },
              "vertical": {
                "attachment": "start",
                "offset": "5.0"
              }
            },
            "tap-handler": "$Menu",
            "size-constraints": {
              "width-constraints": {
                "sizing-mode": "fixed",
                "value": "25.0"
              },
              "height-constraints": {
                "sizing-mode": "fixed",
                "value": "30.0"
              }
            },
            "is-structured": "false",
            "children": [
              "Menu1"
            ],
            "clip-content": "false"
          },
          {
            "id": "Clip path group",
            "margin": {
              "left": "25.0",
              "top": "0.02117919921875",
              "right": "0.003173828125",
              "bottom": "2.66668701171875"
            },
            "is-structured": "false",
            "children": [
              "573b9caeaf",
              "Group"
            ],
            "clip-content": "false"
          },
          {
            "id": "Clip path group1",
            "margin": {
              "left": "109.327392578125",
              "bottom": "2.6878662109375"
            },
            "is-structured": "false",
            "children": [
              "b4bab9ea00",
              "Group6"
            ],
            "clip-content": "false"
          },
          {
            "id": "Logo",
            "alignment": {
              "horizontal": {
                "attachment": "start",
                "offset": "0.0"
              },
              "vertical": {
                "attachment": "start",
                "offset": "6.0"
              }
            },
            "size-constraints": {
              "width-constraints": {
                "sizing-mode": "fixed",
                "value": "25.0"
              },
              "height-constraints": {
                "sizing-mode": "fixed",
                "value": "31.66668701171875"
              }
            },
            "is-structured": "false",
            "children": [
              "Clip path group2"
            ],
            "clip-content": "false"
          },
          {
            "id": "573b9caeaf",
            "is-structured": "false",
            "children": [
              "Vector1"
            ],
            "clip-content": "false"
          },
          {
            "id": "Group",
            "is-structured": "false",
            "children": [
              "Mask group"
            ],
            "clip-content": "false"
          },
          {
            "id": "Vector1",
            "size-constraints": {
              "width-constraints": {
                "sizing-mode": "proportional",
                "value": "1.0"
              },
              "height-constraints": {
                "sizing-mode": "proportional",
                "value": "1.0"
              }
            },
            "vector-content": "vector1.svg"
          },
          {
            "id": "Mask group",
            "is-structured": "false",
            "children": [
              "Group1",
              "Group2"
            ],
            "clip-content": "false"
          },
          {
            "id": "Group1",
            "is-structured": "false",
            "children": [
              "Group3"
            ],
            "clip-content": "false"
          },
          {
            "id": "Group2",
            "is-structured": "false",
            "children": [
              "Group5"
            ],
            "clip-content": "false"
          },
          {
            "id": "Group3",
            "is-structured": "false",
            "children": [
              "Group4"
            ],
            "clip-content": "false"
          },
          {
            "id": "Group4",
            "is-structured": "false",
            "children": [
              "Rectangle"
            ],
            "clip-content": "false"
          },
          {
            "id": "Rectangle",
            "alignment": {
              "horizontal": {
                "attachment": "start",
                "offset": "0.0"
              },
              "vertical": {
                "attachment": "start",
                "offset": "1.94732666015625"
              }
            },
            "size-constraints": {
              "width-constraints": {
                "sizing-mode": "proportional",
                "value": "1.0"
              },
              "height-constraints": {
                "sizing-mode": "proportional",
                "value": "1.0"
              }
            },
            "image-content": "rectangle.png",
            "scale": "fill"
          },
          {
            "id": "Group5",
            "is-structured": "false",
            "children": [
              "Rectangle1"
            ],
            "clip-content": "false"
          },
          {
            "id": "Rectangle1",
            "alignment": {
              "horizontal": {
                "attachment": "start",
                "offset": "0.0"
              },
              "vertical": {
                "attachment": "start",
                "offset": "1.94732666015625"
              }
            },
            "size-constraints": {
              "width-constraints": {
                "sizing-mode": "proportional",
                "value": "1.0"
              },
              "height-constraints": {
                "sizing-mode": "proportional",
                "value": "1.0"
              }
            },
            "image-content": "rectangle1.png",
            "scale": "fill"
          },
          {
            "id": "b4bab9ea00",
            "is-structured": "false",
            "children": [
              "Vector2"
            ],
            "clip-content": "false"
          },
          {
            "id": "Group6",
            "is-structured": "false",
            "children": [
              "Group7"
            ],
            "clip-content": "false"
          },
          {
            "id": "Vector2",
            "size-constraints": {
              "width-constraints": {
                "sizing-mode": "proportional",
                "value": "1.0"
              },
              "height-constraints": {
                "sizing-mode": "proportional",
                "value": "1.0"
              }
            },
            "vector-content": "vector2.svg"
          },
          {
            "id": "Group7",
            "is-structured": "false",
            "children": [
              "Rectangle2"
            ],
            "clip-content": "false"
          },
          {
            "id": "Rectangle2",
            "alignment": {
              "horizontal": {
                "attachment": "start",
                "offset": "84.32476806640625"
              },
              "vertical": {
                "attachment": "start",
                "offset": "1.94683837890625"
              }
            },
            "size-constraints": {
              "width-constraints": {
                "sizing-mode": "proportional",
                "value": "1.0"
              },
              "height-constraints": {
                "sizing-mode": "proportional",
                "value": "1.0"
              }
            },
            "image-content": "rectangle2.png",
            "scale": "fill"
          },
          {
            "id": "Clip path group2",
            "is-structured": "false",
            "children": [
              "695a20c734",
              "Group8"
            ],
            "clip-content": "false"
          },
          {
            "id": "695a20c734",
            "is-structured": "false",
            "children": [
              "Vector3"
            ],
            "clip-content": "false"
          },
          {
            "id": "Group8",
            "is-structured": "false",
            "children": [
              "Group9"
            ],
            "clip-content": "false"
          },
          {
            "id": "Vector3",
            "size-constraints": {
              "width-constraints": {
                "sizing-mode": "proportional",
                "value": "1.0"
              },
              "height-constraints": {
                "sizing-mode": "proportional",
                "value": "1.0"
              }
            },
            "vector-content": "vector3.svg"
          },
          {
            "id": "Group9",
            "is-structured": "false",
            "children": [
              "Rectangle3"
            ],
            "clip-content": "false"
          },
          {
            "id": "Rectangle3",
            "alignment": {
              "horizontal": {
                "attachment": "start",
                "offset": "9.32550048828125"
              },
              "vertical": {
                "attachment": "start",
                "offset": "0.0242919921875"
              }
            },
            "size-constraints": {
              "width-constraints": {
                "sizing-mode": "proportional",
                "value": "1.0"
              },
              "height-constraints": {
                "sizing-mode": "proportional",
                "value": "1.0"
              }
            },
            "image-content": "rectangle3.png",
            "scale": "fill"
          },
          {
            "id": "Menu1",
            "size-constraints": {
              "width-constraints": {
                "sizing-mode": "proportional",
                "value": "1.0"
              },
              "height-constraints": {
                "sizing-mode": "proportional",
                "value": "1.0"
              }
            },
            "image-content": "menu.png",
            "scale": "contain"
          }
        ]
      }
    }
  },
  "parameters": {
    "Next": {
      "data-type": "void-callback",
      "required": false,
      "description": ""
    },
    "Menu": {
      "data-type": "void-callback",
      "required": false,
      "description": ""
    }
  },
  "previews": [
    {
      "design": "Dashboard",
      "size": {
        "width": 360.0,
        "height": 800.0
      }
    }
  ],
  "adin-component-search-paths": [],
  "image-search-paths": [],
  "vector-search-paths": []
}